mail/__init__.py
mail/api.py
mail/cli.py
mail/client.py
mail/server.py
mail/summarizer.py
mail/url_scheme.py
mail/config/__init__.py
mail/config/client.py
mail/config/server.py
mail/core/__init__.py
mail/core/actions.py
mail/core/agents.py
mail/core/message.py
mail/core/runtime.py
mail/core/tasks.py
mail/core/tools.py
mail/db/__init__.py
mail/db/init.py
mail/db/types.py
mail/db/utils.py
mail/examples/__init__.py
mail/examples/analyst_dummy/__init__.py
mail/examples/analyst_dummy/agent.py
mail/examples/analyst_dummy/prompts.py
mail/examples/consultant_dummy/__init__.py
mail/examples/consultant_dummy/agent.py
mail/examples/consultant_dummy/prompts.py
mail/examples/data_analysis/__init__.py
mail/examples/data_analysis/analyst/__init__.py
mail/examples/data_analysis/analyst/agent.py
mail/examples/data_analysis/analyst/prompts.py
mail/examples/data_analysis/processor/__init__.py
mail/examples/data_analysis/processor/actions.py
mail/examples/data_analysis/processor/agent.py
mail/examples/data_analysis/processor/prompts.py
mail/examples/data_analysis/reporter/__init__.py
mail/examples/data_analysis/reporter/actions.py
mail/examples/data_analysis/reporter/agent.py
mail/examples/data_analysis/reporter/prompts.py
mail/examples/data_analysis/statistics/__init__.py
mail/examples/data_analysis/statistics/actions.py
mail/examples/data_analysis/statistics/agent.py
mail/examples/data_analysis/statistics/prompts.py
mail/examples/mafia/__init__.py
mail/examples/mafia/game.py
mail/examples/mafia/narrator_tools.py
mail/examples/mafia/personas.py
mail/examples/mafia/prompts.py
mail/examples/mafia/roles.py
mail/examples/mafia/spec.md
mail/examples/math_dummy/__init__.py
mail/examples/math_dummy/actions.py
mail/examples/math_dummy/agent.py
mail/examples/math_dummy/prompts.py
mail/examples/math_dummy/types.py
mail/examples/research/__init__.py
mail/examples/research/researcher/__init__.py
mail/examples/research/researcher/agent.py
mail/examples/research/researcher/prompts.py
mail_swarms-1.3.2.dist-info/METADATA
mail_swarms-1.3.2.dist-info/WHEEL
mail_swarms-1.3.2.dist-info/entry_points.txt
mail_swarms-1.3.2.dist-info/licenses/LICENSE
mail_swarms-1.3.2.dist-info/licenses/NOTICE
mail_swarms-1.3.2.dist-info/licenses/THIRD_PARTY_NOTICES.md
mail_swarms-1.3.2.dist-info/RECORD
