Metadata-Version: 2.4
Name: mail-swarms
Version: 1.3.2
Summary: Multi-Agent Interface Layer reference implementation
License-Expression: Apache-2.0
License-File: LICENSE
License-File: NOTICE
License-File: THIRD_PARTY_NOTICES.md
Classifier: License :: OSI Approved :: Apache Software License
Requires-Python: >=3.12
Requires-Dist: aiohttp>=3.9.0
Requires-Dist: asyncpg>=0.31.0
Requires-Dist: dict2xml>=1.7.7
Requires-Dist: fastapi>=0.104.1
Requires-Dist: fastmcp>=2.12.5
Requires-Dist: langchain-core>=0.3.72
Requires-Dist: langchain>=0.3.27
Requires-Dist: langgraph>=0.6.3
Requires-Dist: langmem>=0.0.29
Requires-Dist: litellm>=1.76.2
Requires-Dist: numpydoc>=1.9.0
Requires-Dist: openai>=1.106.1
Requires-Dist: pydantic>=2.11.7
Requires-Dist: pyjwt>=2.10.1
Requires-Dist: rich>=13.0.0
Requires-Dist: sse-starlette>=3.0.2
Requires-Dist: toml>=0.10.2
Requires-Dist: types-toml>=0.10.8.20240310
Requires-Dist: types-ujson>=5.10.0.20250822
Requires-Dist: ujson>=5.8.0
Requires-Dist: uvicorn>=0.24.0
